Metadata-Version: 1.1
Name: time-delta
Version: 0.0.0
Summary: Calculate your time by entering the delta between your time and UTC time
Home-page: UNKNOWN
Author: mohammed yasser
Author-email: muhammedyasser85@gmail.com
License: MIT
Keywords: time_delta
Platform: UNKNOWN
Classifier: Development Status :: 5 - Production/Stable
Classifier: Intended Audience :: Education
Classifier: Operating System :: Microsoft :: Windows :: Windows 10
Classifier: License :: OSI Approved :: MIT License
Classifier: Programming Language :: Python :: 3
